CHANGELOG.md
testbrain/__init__.py
testbrain/cli/__init__.py
testbrain/cli/apps/__init__.py
testbrain/cli/apps/auth/__init__.py
testbrain/cli/apps/auth/cli.py
testbrain/cli/apps/project/__init__.py
testbrain/cli/apps/project/cli.py
testbrain/cli/apps/report/__init__.py
testbrain/cli/apps/report/cli.py
testbrain/cli/apps/report/client.py
testbrain/cli/apps/report/utils.py
testbrain/cli/apps/repository/__init__.py
testbrain/cli/apps/repository/cli.py
testbrain/cli/apps/repository/git/__init__.py
testbrain/cli/apps/repository/git/cli.py
testbrain/cli/apps/repository/git/client.py
testbrain/cli/apps/repository/git/exceptions.py
testbrain/cli/apps/repository/git/models.py
testbrain/cli/apps/repository/git/services.py
testbrain/cli/apps/repository/tfvc/__init__.py
testbrain/cli/apps/repository/tfvc/cli.py
testbrain/cli/apps/testsuite/__init__.py
testbrain/cli/apps/testsuite/cli.py
testbrain/cli/cli.py
testbrain/cli/core/__init__.py
testbrain/cli/core/command.py
testbrain/cli/core/context.py
testbrain/cli/core/logging.py
appsurify_testbrain_cli-2024.1.27.dist-info/METADATA
appsurify_testbrain_cli-2024.1.27.dist-info/WHEEL
appsurify_testbrain_cli-2024.1.27.dist-info/entry_points.txt
appsurify_testbrain_cli-2024.1.27.dist-info/RECORD
